Mikado/__init__.py
Mikado/exceptions.py
Mikado/version.py
Mikado/configuration/__init__.py
Mikado/configuration/configuration_blueprint.json
Mikado/configuration/configurator.py
Mikado/configuration/daijin_configurator.py
Mikado/configuration/daijin_schema.json
Mikado/configuration/requirements_blueprint.json
Mikado/configuration/scoring_blueprint.json
Mikado/configuration/scoring_files/athaliana_scoring.yaml
Mikado/configuration/scoring_files/celegans_scoring.yaml
Mikado/configuration/scoring_files/dmelanogaster_scoring.yaml
Mikado/configuration/scoring_files/hsapiens_scoring.yaml
Mikado/configuration/scoring_files/human.yaml
Mikado/configuration/scoring_files/insects.yaml
Mikado/configuration/scoring_files/plants.yaml
Mikado/configuration/scoring_files/scerevisiae.yaml
Mikado/configuration/scoring_files/worm.yaml
Mikado/daijin/__init__.py
Mikado/daijin/example_config.yaml
Mikado/daijin/hpc.json
Mikado/daijin/hpc.yaml
Mikado/daijin/mikado.snakefile
Mikado/daijin/tr.snakefile
Mikado/loci/__init__.py
Mikado/loci/abstractlocus.py
Mikado/loci/excluded.py
Mikado/loci/locus.py
Mikado/loci/monosublocus.py
Mikado/loci/monosublocusholder.py
Mikado/loci/reference_gene.py
Mikado/loci/sublocus.py
Mikado/loci/superlocus.py
Mikado/parsers/GFF.py
Mikado/parsers/GTF.py
Mikado/parsers/__init__.py
Mikado/parsers/bed12.py
Mikado/parsers/blast_utils.py
Mikado/parsers/blast_xml.py
Mikado/parsers/gfannotation.py
Mikado/picking/__init__.py
Mikado/picking/loci_processer.py
Mikado/picking/picker.py
Mikado/preparation/__init__.py
Mikado/preparation/annotation_parser.py
Mikado/preparation/checking.py
Mikado/preparation/prepare.py
Mikado/scales/__init__.py
Mikado/scales/accountant.py
Mikado/scales/assigner.py
Mikado/scales/class_codes.py
Mikado/scales/compare.py
Mikado/scales/contrast.c
Mikado/scales/contrast.cpython-36m-darwin.so
Mikado/scales/contrast.pxd
Mikado/scales/contrast.pyx
Mikado/scales/f1.c
Mikado-1.2.4.dist-info/METADATA
Mikado-1.2.4.dist-info/RECORD
Mikado-1.2.4.dist-info/WHEEL
Mikado-1.2.4.dist-info/entry_points.txt
Mikado-1.2.4.dist-info/top_level.txt
