Metadata-Version: 2.1
Name: Mikado
Version: 1.2.4
Summary: A Python3 annotation program to select the best gene model in each locus
Home-page: https://github.com/lucventurini/mikado
Author: Luca Venturini
Author-email: luca.venturini@earlham.ac.uk
License: GPL3
Keywords: rna-seq annotation genomics transcriptomics
Platform: UNKNOWN
Classifier: Development Status :: 4 - Beta
Classifier: Topic :: Scientific/Engineering :: Bio-Informatics
Classifier: License :: OSI Approved :: GNU Lesser General Public License v3 or later (LGPLv3+)
Classifier: Operating System :: POSIX :: Linux
Classifier: Programming Language :: Python :: 3.4
Classifier: Programming Language :: Python :: 3.5
Classifier: Programming Language :: Python :: 3.6
Provides-Extra: bam
Provides-Extra: postgresql
Provides-Extra: mysql
Requires-Dist: wheel (>=0.28.0)
Requires-Dist: pyyaml
Requires-Dist: jsonschema
Requires-Dist: cython (>=0.25)
Requires-Dist: numpy
Requires-Dist: networkx (>=1.10)
Requires-Dist: sqlalchemy (>=1)
Requires-Dist: sqlalchemy-utils
Requires-Dist: biopython (>=1.66)
Requires-Dist: intervaltree
Requires-Dist: nose
Requires-Dist: pyfaidx
Requires-Dist: scikit-learn (>=0.17.0)
Requires-Dist: scipy (>=0.15.0)
Requires-Dist: frozendict
Requires-Dist: python-magic
Requires-Dist: drmaa
Requires-Dist: docutils (!=0.13.1)
Requires-Dist: tabulate
Requires-Dist: ujson
Requires-Dist: simplejson
Requires-Dist: snakemake (<4.0.0); python_version < "3.5"
Requires-Dist: typing; python_version < "3.5"
Requires-Dist: snakemake; python_version >= "3.5"
Provides-Extra: bam
Requires-Dist: pysam (>=0.8); extra == 'bam'
Provides-Extra: mysql
Requires-Dist: mysqlclient (>=1.3.6); extra == 'mysql'
Provides-Extra: postgresql
Requires-Dist: psycopg2; extra == 'postgresql'
